pykp/__init__.py
pykp/knapsack/__init__.py
pykp/knapsack/_arrangement.py
pykp/knapsack/_item.py
pykp/knapsack/_knapsack.py
pykp/metrics/__init__.py
pykp/metrics/_phase_transition.py
pykp/metrics/_sahni_k.py
pykp/sampling/__init__.py
pykp/sampling/_sampler.py
pykp/solvers/__init__.py
pykp/solvers/_branch_and_bound.py
pykp/solvers/_brute_force.py
pykp/solvers/_greedy.py
pykp/solvers/_minizinc.py
pykp/solvers/_solution.py
pykp-4.2.0.dist-info/LICENSE
pykp-4.2.0.dist-info/METADATA
pykp-4.2.0.dist-info/WHEEL
pykp-4.2.0.dist-info/top_level.txt
pykp-4.2.0.dist-info/RECORD
