Metadata-Version: 2.2
Name: pykp
Version: 4.2.0
Summary: Tooling for sampling and solving instances of the 0-1 Knapsack Problem.
Author-email: Hassan Andrabi <hrs.andrabi@gmail.com>
License: MIT
Project-URL: Homepage, https://github.com/HRSAndrabi/pykp
Project-URL: Documentation, https://github.com/HRSAndrabi/pykp
Project-URL: Repository, https://github.com/HRSAndrabi/pykp
Project-URL: Issues, https://github.com/HRSAndrabi/pykp/issues
Keywords: knapsack,optimisation,sampling,algorithms
Classifier: Intended Audience :: Science/Research
Classifier: Intended Audience :: Developers
Classifier: License :: OSI Approved :: MIT License
Classifier: Programming Language :: Python :: 3.12
Classifier: Operating System :: OS Independent
Classifier: Topic :: Scientific/Engineering
Classifier: Topic :: Scientific/Engineering :: Mathematics
Classifier: Topic :: Software Development :: Libraries :: Python Modules
Requires-Python: >=3.12
License-File: LICENSE
Requires-Dist: pandas>=2.2.3
Requires-Dist: matplotlib==3.9.2
Requires-Dist: numpy==2.1.3
Requires-Dist: networkx==3.4.2
Requires-Dist: tqdm==4.66.6
Requires-Dist: nest-asyncio==1.6.0
Requires-Dist: minizinc==0.9.0
Provides-Extra: test
Requires-Dist: numpy==2.1.3; extra == "test"
Requires-Dist: pytest; extra == "test"
Requires-Dist: pytest-cov; extra == "test"
Requires-Dist: pytest-timeout; extra == "test"
Provides-Extra: dev
Requires-Dist: ruff; extra == "dev"
Provides-Extra: doc
Requires-Dist: Sphinx==8.1.3; extra == "doc"
Requires-Dist: sphinx-autobuild==2024.10.3; extra == "doc"
Requires-Dist: sphinx-copybutton==0.5.2; extra == "doc"
Requires-Dist: sphinx-favicon==1.0.1; extra == "doc"
Requires-Dist: sphinx-sitemap==2.6.0; extra == "doc"
Requires-Dist: sphinx_design==0.6.1; extra == "doc"
Requires-Dist: pydata-sphinx-theme==0.16.1; extra == "doc"
Requires-Dist: numpydoc; extra == "doc"
Requires-Dist: numpy==2.1.3; extra == "doc"
Requires-Dist: tqdm==4.66.6; extra == "doc"
Requires-Dist: matplotlib==3.10.0; extra == "doc"
